{
    "sectors": [
        {
            "z1": 0,
            "z2": 40,
            "ct": 1,
            "cb": 2,
            "d": 0,
            "surf": [
                0,
                0,
                0,
                0,
                0,
                0,
                0,
                0,
                0,
                0,
                0,
                0,
                0,
                0,
                0,
                0,
                0,
                0,
                0,
                0,
                0,
                0,
                0,
                0,
                0,
                0,
                0,
                0,
                0,
                0,
                0,
                0,
                0,
                0,
                0,
                0,
                0,
                0,
                0,
                0,
                0,
                0,
                0,
                0,
                0,
                0,
                0,
                0,
                0,
                0,
                0,
                0,
                0,
                0,
                0,
                0,
                0,
                0,
                0,
                0,
                0,
                0,
                0,
                0,
                0,
                0,
                0,
                0,
                0,
                0,
                0,
                0,
                0,
                0,
                0,
                0,
                0,
                0,
                0,
                0,
                0,
                0,
                0,
                0,
                0,
                0,
                0,
                0,
                0,
                0,
                0,
                0,
                0,
                0,
                0,
                0,
                0,
                0,
                0,
                0,
                0,
                0,
                0,
                0,
                0,
                0,
                0,
                0,
                0,
                0,
                0,
                0,
                0,
                0,
                0,
                0,
                0,
                0,
                0,
                0,
                0,
                0,
                0,
                0,
                0,
                0,
                0,
                0,
                0,
                0,
                0,
                0,
                0,
                0,
                0,
                0,
                0,
                0,
                0,
                0,
                0,
                0,
                0,
                0,
                0,
                0,
                0,
                0,
                0,
                0,
                0,
                0,
                0,
                0,
                0,
                0,
                0,
                0,
                0,
                0
            ],
            "surface": 0,
            "walls": [
                {
                    "x1": 128,
                    "x2": 320,
                    "y1": 128,
                    "y2": 128,
                    "wt_index": 1,
                    "c": [
                        255,
                        0,
                        0
                    ]
                },
                {
                    "x1": 320,
                    "x2": 320,
                    "y1": 128,
                    "y2": 160,
                    "wt_index": 1,
                    "c": [
                        255,
                        0,
                        0
                    ]
                },
                {
                    "x1": 320,
                    "x2": 128,
                    "y1": 160,
                    "y2": 160,
                    "wt_index": 1,
                    "c": [
                        255,
                        0,
                        0
                    ]
                },
                {
                    "x1": 128,
                    "x2": 128,
                    "y1": 160,
                    "y2": 128,
                    "wt_index": 1,
                    "c": [
                        255,
                        0,
                        0
                    ]
                }
            ]
        }
    ]
}